waityapi/__init__.py
waityapi/_base_client.py
waityapi/_client.py
waityapi/_compat.py
waityapi/_constants.py
waityapi/_exceptions.py
waityapi/_files.py
waityapi/_models.py
waityapi/_qs.py
waityapi/_resource.py
waityapi/_response.py
waityapi/_streaming.py
waityapi/_types.py
waityapi/_version.py
waityapi/py.typed
waityapi/_utils/__init__.py
waityapi/_utils/_compat.py
waityapi/_utils/_datetime_parse.py
waityapi/_utils/_logs.py
waityapi/_utils/_proxy.py
waityapi/_utils/_reflection.py
waityapi/_utils/_resources_proxy.py
waityapi/_utils/_streams.py
waityapi/_utils/_sync.py
waityapi/_utils/_transform.py
waityapi/_utils/_typing.py
waityapi/_utils/_utils.py
waityapi/lib/.keep
waityapi/resources/__init__.py
waityapi/resources/health.py
waityapi/resources/partner/__init__.py
waityapi/resources/partner/partner.py
waityapi/resources/partner/stores.py
waityapi/types/__init__.py
waityapi/types/health_check_response.py
waityapi/types/partner/__init__.py
waityapi/types/partner/check_in_response.py
waityapi/types/partner/check_out_response.py
waityapi/types/partner/queue_history.py
waityapi/types/partner/queue_status.py
waityapi/types/partner/store.py
waityapi/types/partner/store_list_response.py
waityapi/types/partner/store_queue_check_in_params.py
waityapi/types/partner/store_queue_check_out_params.py
waityapi/types/partner/store_queue_history_params.py
waityapi/types/partner/store_update_queue_params.py
waityapi/types/partner/store_update_queue_response.py
waityapi/types/partner/store_update_wait_time_params.py
waityapi/types/partner/wait_time.py
waityapi/types/shared/__init__.py
waityapi/types/shared/error_response.py
waityapi-0.3.0.dist-info/METADATA
waityapi-0.3.0.dist-info/WHEEL
waityapi-0.3.0.dist-info/licenses/LICENSE
waityapi-0.3.0.dist-info/RECORD
